MultiPyVu/BRT.py
MultiPyVu/CommandChamber.py
MultiPyVu/CommandField.py
MultiPyVu/CommandMultiVu.py
MultiPyVu/CommandRotator.py
MultiPyVu/CommandSdo.py
MultiPyVu/CommandTemperature.py
MultiPyVu/CommandWaitFor.py
MultiPyVu/Command_factory.py
MultiPyVu/ICommand.py
MultiPyVu/IEventManager.py
MultiPyVu/IServer.py
MultiPyVu/MultiVuClient.py
MultiPyVu/MultiVuClient_base.py
MultiPyVu/MultiVuServer.py
MultiPyVu/ParseInputs.py
MultiPyVu/SocketMessage.py
MultiPyVu/SocketMessageClient.py
MultiPyVu/SocketMessageServer.py
MultiPyVu/__init__.py
MultiPyVu/__main__.py
MultiPyVu/__version.py
MultiPyVu/check_windows_esc.py
MultiPyVu/exceptions.py
MultiPyVu/generate_sdo_objects.py
MultiPyVu/instrument.py
MultiPyVu/logging_config.py
MultiPyVu/logging_config.yaml
MultiPyVu/project_vars.py
MultiPyVu/sdo_object.py
MultiPyVu/MultiVuDataFile/MultiVuDataFile.py
MultiPyVu/MultiVuDataFile/__init__.py
MultiPyVu/MultiVuDataFile/__version.py
MultiPyVu/MultiVuDataFile/is_pathname_valid.py
MultiPyVu/font/Play-Bold.ttf
MultiPyVu/font/Play-Regular.ttf
MultiPyVu/font/__init__.py
MultiPyVu/gui/Controller.py
MultiPyVu/gui/IController.py
MultiPyVu/gui/IView.py
MultiPyVu/gui/ViewFactory.py
MultiPyVu/gui/ViewTk.py
MultiPyVu/gui/__init__.py
MultiPyVu/images/Q.png
MultiPyVu/images/QD_logo.jpg
MultiPyVu/images/__init__.py
MultiPyVu/scripts/__init__.py
MultiPyVu/scripts/helper_scripts.py
MultiPyVu/scripts/whats_my_ip_address.cmd
multipyvu-3.5.4.dist-info/licenses/LICENSE
multipyvu-3.5.4.dist-info/METADATA
multipyvu-3.5.4.dist-info/WHEEL
multipyvu-3.5.4.dist-info/top_level.txt
multipyvu-3.5.4.dist-info/RECORD
