Metadata-Version: 2.4
Name: MultiPyVu
Version: 3.5.4
Summary: Control MultiVu using Python
Author-email: Damon D Jackson <djackson@qdusa.com>
Maintainer-email: "Quantum Design, Inc." <apps@qdusa.com>
License: MIT License (MIT)
Project-URL: Quantum Design, https://qdusa.com
Project-URL: Pharos, https://www.qdusa.com/register/account/login
Keywords: Quantum Design,QD,MultiVu,PPMS,DynaCool,MPMS3,VersaLab,OptiCool
Classifier: Programming Language :: Python :: 3
Classifier: License :: OSI Approved :: MIT License
Classifier: Operating System :: OS Independent
Classifier: Intended Audience :: Science/Research
Classifier: Topic :: Scientific/Engineering :: Physics
Classifier: Topic :: Scientific/Engineering :: Chemistry
Classifier: Topic :: Software Development :: Libraries :: Python Modules
Requires-Python: >=3.9
License-File: LICENSE
Requires-Dist: pandas
Requires-Dist: pywin32>=300; platform_system == "Windows"
Requires-Dist: pillow
Requires-Dist: pyyaml
Dynamic: license-file
Dynamic: requires-dist
Dynamic: requires-python
Dynamic: summary
